nonebot_plugin_tarina_lang_turbo/__init__.py
nonebot_plugin_tarina_lang_turbo/exception.py
nonebot_plugin_tarina_lang_turbo/hook.py
nonebot_plugin_tarina_lang_turbo/manager.py
nonebot_plugin_tarina_lang_turbo/matcher.py
nonebot_plugin_tarina_lang_turbo/i18n/.config.json
nonebot_plugin_tarina_lang_turbo/i18n/.lang.schema.json
nonebot_plugin_tarina_lang_turbo/i18n/.template.json
nonebot_plugin_tarina_lang_turbo/i18n/.template.schema.json
nonebot_plugin_tarina_lang_turbo/i18n/__init__.py
nonebot_plugin_tarina_lang_turbo/i18n/en-US.json
nonebot_plugin_tarina_lang_turbo/i18n/model.py
nonebot_plugin_tarina_lang_turbo/i18n/zh-CN.json
nonebot_plugin_tarina_lang_turbo-0.1.1.dist-info/METADATA
nonebot_plugin_tarina_lang_turbo-0.1.1.dist-info/WHEEL
nonebot_plugin_tarina_lang_turbo-0.1.1.dist-info/licenses/LICENSE
nonebot_plugin_tarina_lang_turbo-0.1.1.dist-info/RECORD
