Metadata-Version: 2.3
Name: nonebot-plugin-tarina-lang-turbo
Version: 0.1.1
Summary: Enhance tarina.lang to support user-level configuration
Author-email: shoucandanghehe <wallfjjd@gmail.com>
License: MIT
License-File: LICENSE
Classifier: Programming Language :: Python :: 3 :: Only
Classifier: Programming Language :: Python :: 3.9
Classifier: Programming Language :: Python :: 3.10
Classifier: Programming Language :: Python :: 3.11
Classifier: Programming Language :: Python :: 3.12
Requires-Python: >=3.9
Requires-Dist: msgspec>=0.18.6
Requires-Dist: nonebot-plugin-alconna>=0.52.2
Requires-Dist: nonebot-plugin-localstore>=0.7.1
Requires-Dist: nonebot-plugin-session>=0.3.2
Requires-Dist: nonebot2>=2.3.3
Requires-Dist: tarina>=0.5.8
